actinrings/__init__.py
actinrings/_version.py
actinrings/analytical.py
actinrings/fem_parsing.py
actinrings/plots.py
actinrings-1.1.1.dist-info/LICENSE.txt
actinrings-1.1.1.dist-info/METADATA
actinrings-1.1.1.dist-info/WHEEL
actinrings-1.1.1.dist-info/top_level.txt
actinrings-1.1.1.dist-info/RECORD
