Metadata-Version: 2.1
Name: actinrings
Version: 1.1.1
Summary: Python package for the equilibrium analysis of the paper "Constriction of actin rings by passive crosslinker".
Home-page: https://github.com/cumberworth/actinrings
Author: Alexander Cumberworth
Author-email: alex@cumberworth.org
Project-URL: Paper, https://doi.org/10.48550/arXiv.2203.04260
Project-URL: Replication package for paper, https://doi.org/10.5281/zenodo.6327217
Classifier: Programming Language :: Python :: 3
Classifier: License :: OSI Approved :: MIT License
Classifier: Operating System :: POSIX :: Linux
Requires-Python: >=3.6
License-File: LICENSE.txt
Requires-Dist: matplotlib
Requires-Dist: matplotlibstyles (==0.2.2)
Requires-Dist: numpy
Requires-Dist: pandas
Requires-Dist: scipy
